giantstar/__init__.py
giantstar/_miracle.py
giantstar/cli.py
giantstar/globalSetting.py
giantstar/testFactory.py
giantstar/_locust/__init__.py
giantstar/_locust/locustfile.py
giantstar/assert_/__init__.py
giantstar/assert_/app.py
giantstar/assert_/comparetors.py
giantstar/assert_/publicAssert.py
giantstar/assert_/web.py
giantstar/drivers/__init__.py
giantstar/drivers/appDriver.py
giantstar/drivers/basicDriver.py
giantstar/drivers/compatorDriver.py
giantstar/drivers/debugDriver.py
giantstar/drivers/driverBy.py
giantstar/drivers/httpDriver.py
giantstar/drivers/kwDriver.py
giantstar/drivers/locustDriver.py
giantstar/drivers/webDriver.py
giantstar/loader/__init__.py
giantstar/loader/easyNodeParser.py
giantstar/loader/locustLoader.py
giantstar/loader/nodeParser.py
giantstar/loader/pytestLoader.py
giantstar/sessionManage/__init__.py
giantstar/sessionManage/baseSession.py
giantstar/sessionManage/requestsSession.py
giantstar/sessionManage/appSession/__init__.py
giantstar/sessionManage/appSession/appiumSession.py
giantstar/sessionManage/appSession/devicesManage.py
giantstar/sessionManage/appSession/element.py
giantstar/sessionManage/appSession/openstfController.py
giantstar/sessionManage/webSession/__init__.py
giantstar/sessionManage/webSession/element.py
giantstar/sessionManage/webSession/seleniumSession.py
giantstar/sessionManage/webSession/selenoidController.py
giantstar/sessionManage/webSession/webdrivers/linux/chromedriver
giantstar/sessionManage/webSession/webdrivers/linux/geckodriver
giantstar/sessionManage/webSession/webdrivers/mac/chromedriver
giantstar/sessionManage/webSession/webdrivers/mac/geckodriver
giantstar/sessionManage/webSession/webdrivers/windows/chromedriver.exe
giantstar/sessionManage/webSession/webdrivers/windows/geckodriver.exe
giantstar/template/__init__.py
giantstar/template/hookimpl.py
giantstar/template/locustManage.py
giantstar/template/manage.py
giantstar/template/miracle.py
giantstar/template/run.py
giantstar/template/settings.py
giantstar-1.0.0.dist-info/LICENSE
giantstar-1.0.0.dist-info/METADATA
giantstar-1.0.0.dist-info/WHEEL
giantstar-1.0.0.dist-info/entry_points.txt
giantstar-1.0.0.dist-info/top_level.txt
giantstar-1.0.0.dist-info/RECORD
